[
  {
    "id": 1,
    "title": "The Great Gatsby",
    "author": "F. Scott Fitzgerald",
    "isbn": "9780743273565",
    "price": 10.99,
    "stock": 50,
    "description": "The Great Gatsby is a 1925 novel by American writer F. Scott Fitzgerald.",
    "genre": "Classic",
    "publicationYear": 1925,
    "createdAt": "2023-01-15T08:00:00Z",
    "updatedAt": "2023-01-15T08:00:00Z",
    "image": "https://plus.unsplash.com/premium_photo-1669048776605-28ea2e52ae66?q=80&w=2070&auto=format&fit=crop&ixlib=rb-4.0.3&ixid=M3wxMjA3fDB8MHxwaG90by1wYWdlfHx8fGVufDB8fHx8fA%3D%3D"
  },
  {
    "id": 2,
    "title": "To Kill a Mockingbird",
    "author": "Harper Lee",
    "isbn": "9780061120084",
    "price": 9.99,
    "stock": 40,
    "description": "To Kill a Mockingbird is a novel by Harper Lee published in 1960.",
    "genre": "Classic",
    "publicationYear": 1960,
    "createdAt": "2023-02-20T08:00:00Z",
    "updatedAt": "2023-02-20T08:00:00Z",
    "image": "https://images.unsplash.com/photo-1715271040278-9c6fcd6e669b?q=80&w=2071&auto=format&fit=crop&ixlib=rb-4.0.3&ixid=M3wxMjA3fDB8MHxwaG90by1wYWdlfHx8fGVufDB8fHx8fA%3D%3D"
  },
  {
    "id": 3,
    "title": "1984",
    "author": "George Orwell",
    "isbn": "9780451524935",
    "price": 8.99,
    "stock": 60,
    "description": "1984 is a dystopian social science fiction novel by English writer George Orwell.",
    "genre": "Science Fiction",
    "publicationYear": 1949,
    "createdAt": "2023-03-10T08:00:00Z",
    "updatedAt": "2023-03-10T08:00:00Z",
    "image": "https://plus.unsplash.com/premium_photo-1670985849616-6aa6c441e0bf?q=80&w=2070&auto=format&fit=crop&ixlib=rb-4.0.3&ixid=M3wxMjA3fDB8MHxwaG90by1wYWdlfHx8fGVufDB8fHx8fA%3D%3D"
  },
  {
    "id": 4,
    "title": "Pride and Prejudice",
    "author": "Jane Austen",
    "isbn": "9780141439518",
    "price": 7.99,
    "stock": 55,
    "description": "Pride and Prejudice is a romantic novel of manners written by Jane Austen in 1813.",
    "genre": "Romance",
    "publicationYear": 1813,
    "createdAt": "2023-04-05T08:00:00Z",
    "updatedAt": "2023-04-05T08:00:00Z",
    "image": "https://images.unsplash.com/photo-1715313036312-01d046cd99b8?q=80&w=1974&auto=format&fit=crop&ixlib=rb-4.0.3&ixid=M3wxMjA3fDB8MHxwaG90by1wYWdlfHx8fGVufDB8fHx8fA%3D%3D"
  },
  {
    "id": 5,
    "title": "Harry Potter and the Sorcerer's Stone",
    "author": "J.K. Rowling",
    "isbn": "9780590353403",
    "price": 12.99,
    "stock": 45,
    "description": "Harry Potter and the Philosopher's Stone is a fantasy novel written by British author J. K. Rowling.",
    "genre": "Fantasy",
    "publicationYear": 1997,
    "createdAt": "2023-05-15T08:00:00Z",
    "updatedAt": "2023-05-15T08:00:00Z",
    "image": "https://images.unsplash.com/photo-1715314945142-2980c03c93be?q=80&w=1974&auto=format&fit=crop&ixlib=rb-4.0.3&ixid=M3wxMjA3fDB8MHxwaG90by1wYWdlfHx8fGVufDB8fHx8fA%3D%3D"
  },
  {
    "id": 6,
    "title": "The Catcher in the Rye",
    "author": "J.D. Salinger",
    "isbn": "9780316769488",
    "price": 11.99,
    "stock": 30,
    "description": "The Catcher in the Rye is a novel by J. D. Salinger, partially published in serial form in 1945–1946 and as a novel in 1951.",
    "genre": "Classic",
    "publicationYear": 1951,
    "createdAt": "2023-06-20T08:00:00Z",
    "updatedAt": "2023-06-20T08:00:00Z",
    "image": "https://images.unsplash.com/photo-1715320555601-75fe531bfefe?q=80&w=1974&auto=format&fit=crop&ixlib=rb-4.0.3&ixid=M3wxMjA3fDB8MHxwaG90by1wYWdlfHx8fGVufDB8fHx8fA%3D%3D"
  },
  {
    "id": 7,
    "title": "The Hobbit",
    "author": "J.R.R. Tolkien",
    "isbn": "9780345534835",
    "price": 13.99,
    "stock": 25,
    "description": "The Hobbit, or There and Back Again, is a fantasy novel and children's book by English author J. R. R. Tolkien.",
    "genre": "Fantasy",
    "publicationYear": 1937,
    "createdAt": "2023-07-10T08:00:00Z",
    "updatedAt": "2023-07-10T08:00:00Z",
    "image": "https://images.unsplash.com/photo-1715144536780-c847096a8632?q=80&w=1936&auto=format&fit=crop&ixlib=rb-4.0.3&ixid=M3wxMjA3fDB8MHxwaG90by1wYWdlfHx8fGVufDB8fHx8fA%3D%3D"
  },
  {
    "id": 8,
    "title": "The Lord of the Rings",
    "author": "J.R.R. Tolkien",
    "isbn": "9780261102385",
    "price": 25.99,
    "stock": 20,
    "description": "The Lord of the Rings is an epic high-fantasy novel written by English author and scholar J. R. R. Tolkien.",
    "genre": "Fantasy",
    "publicationYear": 1954,
    "createdAt": "2023-08-05T08:00:00Z",
    "updatedAt": "2023-08-05T08:00:00Z",
    "image": "https://images.unsplash.com/photo-1715276611597-048987ab7d97?q=80&w=1976&auto=format&fit=crop&ixlib=rb-4.0.3&ixid=M3wxMjA3fDB8MHxwaG90by1wYWdlfHx8fGVufDB8fHx8fA%3D%3D"
  },
  {
    "id": 9,
    "title": "Moby-Dick",
    "author": "Herman Melville",
    "isbn": "9781853260087",
    "price": 14.99,
    "stock": 35,
    "description": "Moby-Dick; or, The Whale is an 1851 novel by American writer Herman Melville.",
    "genre": "Adventure",
    "publicationYear": 1851,
    "createdAt": "2023-09-15T08:00:00Z",
    "updatedAt": "2023-09-15T08:00:00Z",
    "image": "https://images.unsplash.com/photo-1714423718253-b1bd2d95ddd9?q=80&w=2070&auto=format&fit=crop&ixlib=rb-4.0.3&ixid=M3wxMjA3fDB8MHxwaG90by1wYWdlfHx8fGVufDB8fHx8fA%3D%3D"
  },
  {
    "id": 10,
    "title": "The Picture of Dorian Gray",
    "author": "Oscar Wilde",
    "isbn": "9780141439570",
    "price": 9.99,
    "stock": 0,
    "description": "The Picture of Dorian Gray is a Gothic and philosophical novel by Oscar Wilde, first published complete in the July 1890 issue of Lippincott's Monthly Magazine.",
    "genre": "Gothic",
    "publicationYear": 1890,
    "createdAt": "2023-10-20T08:00:00Z",
    "updatedAt": "2023-10-20T08:00:00Z",
    "image": "https://images.unsplash.com/photo-1715276611505-fbea90d3e9e3?q=80&w=2069&auto=format&fit=crop&ixlib=rb-4.0.3&ixid=M3wxMjA3fDB8MHxwaG90by1wYWdlfHx8fGVufDB8fHx8fA%3D%3D"
  }
]
